humble_database/__init__.py
humble_database/_modidx.py
humble_database/core.py
humble_database/data_model.py
humble_database/database.py
humble_database/utils.py
humble_database-0.0.1.dist-info/LICENSE
humble_database-0.0.1.dist-info/METADATA
humble_database-0.0.1.dist-info/WHEEL
humble_database-0.0.1.dist-info/entry_points.txt
humble_database-0.0.1.dist-info/top_level.txt
humble_database-0.0.1.dist-info/RECORD
