Metadata-Version: 2.1
Name: humble-database
Version: 0.0.1
Summary: A simple interface for managing database connections and queries
Home-page: https://github.com/schlinkertc/humble-database
Author: Charlie Schlinkert
Author-email: cschlinkert@pretium.com
License: Apache Software License 2.0
Keywords: nbdev jupyter notebook python sqlalchemy pydantic
Classifier: Development Status :: 4 - Beta
Classifier: Intended Audience :: Developers
Classifier: Natural Language :: English
Classifier: Programming Language :: Python :: 3.7
Classifier: Programming Language :: Python :: 3.8
Classifier: Programming Language :: Python :: 3.9
Classifier: Programming Language :: Python :: 3.10
Classifier: License :: OSI Approved :: Apache Software License
Requires-Python: >=3.7
License-File: LICENSE
Requires-Dist: fastcore
Requires-Dist: pandas
Requires-Dist: sqlalchemy
Requires-Dist: pydantic
Requires-Dist: pydantic-settings
Requires-Dist: json2html
Provides-Extra: dev
Requires-Dist: psycopg2 ; extra == 'dev'
